braintumorpredict-0.0.1.dist-info/licenses/LICENSE
braintumorprediction/__init__.py
braintumorprediction/prediction.py
braintumorpredict-0.0.1.dist-info/METADATA
braintumorpredict-0.0.1.dist-info/WHEEL
braintumorpredict-0.0.1.dist-info/top_level.txt
braintumorpredict-0.0.1.dist-info/RECORD
