Metadata-Version: 2.4
Name: braintumorpredict
Version: 0.0.1
Summary: 2025 Python project.
Author-email: Ahmet Serdar Erol <as.erol2042@gmail.com>
License: MIT License
Project-URL: Homepage, https://github.com/AhmetSerdarErol/braintumorprediction
Keywords: brain,tumor,python
Classifier: Development Status :: 3 - Alpha
Classifier: Intended Audience :: Developers
Classifier: Programming Language :: Python :: 3
Classifier: Operating System :: OS Independent
Requires-Python: >=3.6.0
License-File: LICENSE
Dynamic: license-file
